akash/__init__.py
akash/client.py
akash/grpc_client.py
akash/py.typed
akash/tx.py
akash/wallet.py
akash/messages/__init__.py
akash/messages/audit.py
akash/messages/authz.py
akash/messages/bank.py
akash/messages/cert.py
akash/messages/deployment.py
akash/messages/distribution.py
akash/messages/evidence.py
akash/messages/feegrant.py
akash/messages/governance.py
akash/messages/ibc.py
akash/messages/market.py
akash/messages/provider.py
akash/messages/slashing.py
akash/messages/staking.py
akash/modules/__init__.py
akash/modules/audit/__init__.py
akash/modules/audit/client.py
akash/modules/audit/query.py
akash/modules/audit/tx.py
akash/modules/audit/utils.py
akash/modules/auth/__init__.py
akash/modules/auth/client.py
akash/modules/auth/query.py
akash/modules/auth/utils.py
akash/modules/authz/__init__.py
akash/modules/authz/client.py
akash/modules/authz/query.py
akash/modules/authz/tx.py
akash/modules/authz/utils.py
akash/modules/bank/__init__.py
akash/modules/bank/client.py
akash/modules/bank/query.py
akash/modules/bank/tx.py
akash/modules/bank/utils.py
akash/modules/cert/__init__.py
akash/modules/cert/client.py
akash/modules/cert/query.py
akash/modules/cert/tx.py
akash/modules/cert/utils.py
akash/modules/deployment/__init__.py
akash/modules/deployment/client.py
akash/modules/deployment/query.py
akash/modules/deployment/tx.py
akash/modules/deployment/utils.py
akash/modules/discovery/__init__.py
akash/modules/discovery/client.py
akash/modules/discovery/query.py
akash/modules/discovery/utils.py
akash/modules/distribution/__init__.py
akash/modules/distribution/client.py
akash/modules/distribution/query.py
akash/modules/distribution/tx.py
akash/modules/escrow/__init__.py
akash/modules/escrow/client.py
akash/modules/escrow/query.py
akash/modules/evidence/__init__.py
akash/modules/evidence/client.py
akash/modules/evidence/query.py
akash/modules/evidence/tx.py
akash/modules/evidence/utils.py
akash/modules/feegrant/__init__.py
akash/modules/feegrant/client.py
akash-0.6.0.dist-info/licenses/LICENSE
akash-0.6.0.dist-info/METADATA
akash-0.6.0.dist-info/WHEEL
akash-0.6.0.dist-info/entry_points.txt
akash-0.6.0.dist-info/top_level.txt
akash-0.6.0.dist-info/RECORD
