Metadata-Version: 2.4
Name: akash
Version: 0.6.0
Summary: Python SDK for Akash Network - interact with the blockchain and deploy and manage workloads on the decentralized cloud
Author-email: Akash community <contact@cosmosrescue.com>
License: Apache-2.0
Project-URL: Homepage, https://github.com/cosmosrescue/akash-py
Project-URL: Documentation, https://akash-py.cosmosrescue.com
Project-URL: Repository, https://github.com/cosmosrescue/akash-py
Project-URL: Bug Tracker, https://github.com/cosmosrescue/akash-py/issues
Project-URL: Akash Network, https://akash.network/
Project-URL: Akash Docs, https://docs.akash.network/
Keywords: akash,blockchain,kubernetes,cloud,decentralized,deployment,docker,grpc,cosmos,sdk
Classifier: Development Status :: 4 - Beta
Classifier: Intended Audience :: Developers
Classifier: Operating System :: OS Independent
Classifier: Programming Language :: Python :: 3
Classifier: Programming Language :: Python :: 3.8
Classifier: Programming Language :: Python :: 3.9
Classifier: Programming Language :: Python :: 3.10
Classifier: Programming Language :: Python :: 3.11
Classifier: Programming Language :: Python :: 3.12
Classifier: Topic :: Internet :: WWW/HTTP
Classifier: Topic :: Software Development :: Libraries :: Python Modules
Classifier: Topic :: System :: Distributed Computing
Classifier: Topic :: System :: Networking
Requires-Python: >=3.8
License-File: LICENSE
Requires-Dist: grpcio>=1.50.0
Requires-Dist: grpclib>=0.4.0
Requires-Dist: protobuf>=4.21.0
Requires-Dist: googleapis-common-protos>=1.57.0
Requires-Dist: ecdsa>=0.18.0
Requires-Dist: bech32>=1.2.0
Requires-Dist: requests>=2.20.0
Requires-Dist: mnemonic>=0.20
Requires-Dist: pycryptodome>=3.15.0
Requires-Dist: cryptography>=41.0.0
Requires-Dist: pyyaml>=5.1.0
Requires-Dist: websocket-client>=1.0.0
Provides-Extra: dev
Requires-Dist: pytest>=6.0; extra == "dev"
Requires-Dist: pytest-cov>=2.10; extra == "dev"
Requires-Dist: black>=22.0; extra == "dev"
Requires-Dist: flake8>=4.0; extra == "dev"
Requires-Dist: mypy>=0.900; extra == "dev"
Requires-Dist: build>=0.8.0; extra == "dev"
Requires-Dist: twine>=4.0.0; extra == "dev"
Provides-Extra: docs
Requires-Dist: sphinx>=4.0; extra == "docs"
Requires-Dist: sphinx-rtd-theme>=1.0; extra == "docs"
Requires-Dist: myst-parser>=0.18; extra == "docs"
Dynamic: license-file
